decogreat/__init__.py
decogreat/decorator_factory.py
decogreat/decorator_protocol.py
decogreat-0.1.1.dist-info/LICENSE
decogreat-0.1.1.dist-info/METADATA
decogreat-0.1.1.dist-info/WHEEL
decogreat-0.1.1.dist-info/RECORD
