Metadata-Version: 2.3
Name: decogreat
Version: 0.1.1
Summary: This package contains the main functionalities
License: MIT
Author: Luis IGLESIAS HERNANDEZ
Requires-Python: >=3.11
Classifier: License :: OSI Approved :: MIT License
Classifier: Programming Language :: Python :: 3
Classifier: Programming Language :: Python :: 3.11
Classifier: Programming Language :: Python :: 3.12
Classifier: Programming Language :: Python :: 3.13
